odoo/addons/account_move_reconciled_date/LICENSE
odoo/addons/account_move_reconciled_date/README.rst
odoo/addons/account_move_reconciled_date/__init__.py
odoo/addons/account_move_reconciled_date/__manifest__.py
odoo/addons/account_move_reconciled_date/i18n/de.po
odoo/addons/account_move_reconciled_date/images/screen.png
odoo/addons/account_move_reconciled_date/models/__init__.py
odoo/addons/account_move_reconciled_date/models/account_move.py
odoo/addons/account_move_reconciled_date/static/description/icon.png
odoo/addons/account_move_reconciled_date/static/description/index.html
odoo/addons/account_move_reconciled_date/tests/TEST_INSTRUCTIONS.rst
odoo/addons/account_move_reconciled_date/views/view_invoice_tree.xml
odoo_addon_account_move_reconciled_date-18.0.1.0.0.dist-info/METADATA
odoo_addon_account_move_reconciled_date-18.0.1.0.0.dist-info/WHEEL
odoo_addon_account_move_reconciled_date-18.0.1.0.0.dist-info/top_level.txt
odoo_addon_account_move_reconciled_date-18.0.1.0.0.dist-info/RECORD
